pdf2u/__init__.py
pdf2u/const.py
pdf2u/converter.py
pdf2u/gui.py
pdf2u/high_level.py
pdf2u/io.py
pdf2u/main.py
pdf2u/pdfinterp.py
pdf2u/progress_monitor.py
pdf2u/py.typed
pdf2u/translation_config.py
pdf2u/asynchronize/__init__.py
pdf2u/document_il/__init__.py
pdf2u/document_il/il_version_1.py
pdf2u/document_il/il_version_1.rnc
pdf2u/document_il/il_version_1.rng
pdf2u/document_il/il_version_1.xsd
pdf2u/document_il/xml_converter.py
pdf2u/document_il/backend/__init__.py
pdf2u/document_il/backend/pdf_creater.py
pdf2u/document_il/frontend/__init__.py
pdf2u/document_il/frontend/il_creater.py
pdf2u/document_il/midend/__init__.py
pdf2u/document_il/midend/add_debug_information.py
pdf2u/document_il/midend/il_translator.py
pdf2u/document_il/midend/layout_parser.py
pdf2u/document_il/midend/paragraph_finder.py
pdf2u/document_il/midend/remove_descent.py
pdf2u/document_il/midend/styles_and_formulas.py
pdf2u/document_il/midend/typesetting.py
pdf2u/document_il/translator/__init__.py
pdf2u/document_il/translator/cache.py
pdf2u/document_il/translator/translator.py
pdf2u/document_il/utils/fontmap.py
pdf2u/document_il/utils/layout_helper.py
pdf2u/document_il/utils/style_helper.py
pdf2u/docvision/README.md
pdf2u/docvision/__init__.py
pdf2u/docvision/doclayout.py
pdf2u/docvision/rpc_doclayout.py
pdf2u-0.0.6.dist-info/METADATA
pdf2u-0.0.6.dist-info/WHEEL
pdf2u-0.0.6.dist-info/entry_points.txt
pdf2u-0.0.6.dist-info/licenses/LICENSE
pdf2u-0.0.6.dist-info/RECORD
